honeybadger/__init__.py
honeybadger/config.py
honeybadger/connection.py
honeybadger/context_store.py
honeybadger/core.py
honeybadger/events_worker.py
honeybadger/fake_connection.py
honeybadger/middleware.py
honeybadger/notice.py
honeybadger/payload.py
honeybadger/plugins.py
honeybadger/protocols.py
honeybadger/types.py
honeybadger/utils.py
honeybadger/version.py
honeybadger/contrib/__init__.py
honeybadger/contrib/asgi.py
honeybadger/contrib/aws_lambda.py
honeybadger/contrib/celery.py
honeybadger/contrib/db.py
honeybadger/contrib/django.py
honeybadger/contrib/fastapi.py
honeybadger/contrib/flask.py
honeybadger/contrib/logger.py
honeybadger-1.1.1.dist-info/licenses/LICENSE
honeybadger-1.1.1.dist-info/METADATA
honeybadger-1.1.1.dist-info/WHEEL
honeybadger-1.1.1.dist-info/top_level.txt
honeybadger-1.1.1.dist-info/RECORD
