Metadata-Version: 2.4
Name: honeybadger
Version: 1.1.1
Summary: Send Python and Django errors to Honeybadger
Home-page: https://github.com/honeybadger-io/honeybadger-python
Author: Dave Sullivan
Author-email: dave@davesullivan.ca
License: MIT
Classifier: Development Status :: 4 - Beta
Classifier: Intended Audience :: Developers
Classifier: License :: OSI Approved :: MIT License
Classifier: Programming Language :: Python :: 3.4
Classifier: Programming Language :: Python :: 3.5
Classifier: Programming Language :: Python :: 3.6
Classifier: Programming Language :: Python :: 3.7
Classifier: Topic :: System :: Monitoring
License-File: LICENSE
Requires-Dist: psutil
Requires-Dist: six
Dynamic: author
Dynamic: author-email
Dynamic: classifier
Dynamic: home-page
Dynamic: license
Dynamic: license-file
Dynamic: requires-dist
Dynamic: summary
